[
  {
    "NOMBRE": "leo",
    "APELLIDO": "mess",
    "CONTRASENA": "a",
    "T1": false,
    "T2": false,
    "T3": false,
    "T4": false,
    "T5": false,
    "T6": false,
    "DOSIS": "2",
    "RATIO": "1",
    "NOMBREniño": "neymar",
    "APELLIDOniño": "jr"
  },
  {
    "NOMBRE": "leo",
    "APELLIDO": "messi",
    "CONTRASENA": "a",
    "T1": false,
    "T2": false,
    "T3": true,
    "T4": false,
    "T5": false,
    "T6": false,
    "DOSIS": "2",
    "RATIO": "1",
    "NOMBREniño": "male",
    "APELLIDOniño": "creosalio"
  },
  {
    "NOMBRE": "naco",
    "APELLIDO": "rossi",
    "CONTRASENA": "123",
    "T1": false,
    "T2": false,
    "T3": false,
    "T4": false,
    "T5": false,
    "T6": false,
    "DOSIS": "2",
    "RATIO": "200",
    "NOMBREniño": "male",
    "APELLIDOniño": "rossii"
  },
  {
    "NOMBRE": "aa",
    "APELLIDO": "messi",
    "CONTRASENA": "a",
    "T1": false,
    "T2": false,
    "T3": false,
    "T4": false,
    "T5": false,
    "T6": false,
    "DOSIS": "2",
    "RATIO": "1",
    "NOMBREniño": "male",
    "APELLIDOniño": "creosalio"
  },
  {
    "NOMBRE": "gerardo",
    "APELLIDO": "tabakman",
    "CONTRASENA": "123",
    "T1": false,
    "T2": false,
    "T3": true,
    "T4": false,
    "T5": false,
    "T6": false,
    "DOSIS": "30",
    "RATIO": "20",
    "NOMBREniño": "maximiliano",
    "APELLIDOniño": "tabakman"
  },
  {
    "NOMBRE": "marina",
    "APELLIDO": "tabakman",
    "CONTRASENA": "123",
    "T1": false,
    "T2": false,
    "T3": true,
    "T4": false,
    "T5": false,
    "T6": false,
    "DOSIS": "30",
    "RATIO": "20",
    "NOMBREniño": "maxi",
    "APELLIDOniño": "tabakman"
  },
  {
    "NOMBRE": "gerardo",
    "APELLIDO": "tabakman",
    "CONTRASENA": "gera",
    "T1": true,
    "T2": false,
    "T3": false,
    "T4": true,
    "T5": true,
    "T6": true,
    "DOSIS": "100",
    "RATIO": "10000",
    "NOMBREniño": "jose",
    "APELLIDOniño": "tabakman"
  },
  {
    "NOMBRE": "micaela",
    "APELLIDO": "tabakman",
    "CONTRASENA": "123",
    "T1": true,
    "T2": true,
    "T3": true,
    "T4": true,
    "T5": true,
    "T6": false,
    "DOSIS": "40",
    "RATIO": "20",
    "NOMBREniño": "susana",
    "APELLIDOniño": "tabakman"
  },
  {
    "NOMBRE": "micaela",
    "APELLIDO": "tabakma",
    "CONTRASENA": "123",
    "T1": true,
    "T2": true,
    "T3": true,
    "T4": true,
    "T5": true,
    "T6": false,
    "DOSIS": "40",
    "RATIO": "20",
    "NOMBREniño": "susana",
    "APELLIDOniño": "tabakman"
  },
  {
    "NOMBRE": "Marto",
    "APELLIDO": "Morales Larroza",
    "CONTRASENA": "1234556",
    "T1": true,
    "T2": true,
    "T3": true,
    "T4": true,
    "T5": true,
    "T6": false,
    "DOSIS": "2",
    "RATIO": "2",
    "NOMBREniño": "Martito",
    "APELLIDOniño": "Morales",
    "CONTRASENAniño": 412
  },
  {
    "NOMBRE": "GONZALO",
    "APELLIDO": "ALVAREZ",
    "CONTRASENA": "12345678",
    "T1": true,
    "T2": true,
    "T3": false,
    "T4": false,
    "T5": true,
    "T6": true,
    "DOSIS": "4",
    "RATIO": "100",
    "NOMBREniño": "MALENA",
    "APELLIDOniño": "ROSSI",
    "CONTRASENAniño": 1522
  },
  {
    "NOMBRE": "Carlo",
    "APELLIDO": "Morales Larroza",
    "CONTRASENA": "123567843",
    "T1": true,
    "T2": false,
    "T3": false,
    "T4": false,
    "T5": false,
    "T6": false,
    "DOSIS": "1",
    "RATIO": "1",
    "NOMBREniño": "Vinicius",
    "APELLIDOniño": "Junior",
    "CONTRASENAniño": 222
  }
]